swarmauri_parser_entityrecognition/EntityRecognitionParser.py
swarmauri_parser_entityrecognition/__init__.py
swarmauri_parser_entityrecognition-0.6.7.dist-info/LICENSE
swarmauri_parser_entityrecognition-0.6.7.dist-info/METADATA
swarmauri_parser_entityrecognition-0.6.7.dist-info/WHEEL
swarmauri_parser_entityrecognition-0.6.7.dist-info/entry_points.txt
swarmauri_parser_entityrecognition-0.6.7.dist-info/RECORD
