Metadata-Version: 2.3
Name: swarmauri_parser_entityrecognition
Version: 0.6.7
Summary: Entity Recognition Parser for Swarmauri.
License: Apache-2.0
Author: Jacob Stewart
Author-email: jacob@swarmauri.com
Requires-Python: >=3.10,<3.13
Classifier: License :: OSI Approved :: Apache Software License
Classifier: Programming Language :: Python :: 3.10
Classifier: Programming Language :: Python :: 3.11
Classifier: Programming Language :: Python :: 3.12
Requires-Dist: spacy (>=3.7.0,<3.8.0)
Requires-Dist: spacy-lookups-data (>=1.0.5)
Requires-Dist: swarmauri_base
Requires-Dist: swarmauri_core
Requires-Dist: swarmauri_standard
